typedhtml/__init__.py
typedhtml/attributes.py
typedhtml/document.py
typedhtml/events.py
typedhtml/globals.py
typedhtml/ionic/__init__.py
typedhtml/ionic/accordion.py
typedhtml/ionic/action_sheet.py
typedhtml/ionic/alert.py
typedhtml/ionic/app.py
typedhtml/ionic/badge.py
typedhtml/ionic/base.py
typedhtml/ionic/breadcrumbs.py
typedhtml/ionic/button.py
typedhtml/ionic/card.py
typedhtml/ionic/checkbox.py
typedhtml/ionic/chip.py
typedhtml/ionic/content.py
typedhtml/ionic/date_time.py
typedhtml/ionic/fab.py
typedhtml/ionic/grid.py
typedhtml/ionic/icon.py
typedhtml/ionic/indicators.py
typedhtml/ionic/infinite_scroll.py
typedhtml/ionic/input_.py
typedhtml/ionic/item.py
typedhtml/ionic/list_.py
typedhtml/ionic/media.py
typedhtml/ionic/menu.py
typedhtml/ionic/modal.py
typedhtml/ionic/nav.py
typedhtml/ionic/picker.py
typedhtml/ionic/popover.py
typedhtml/ionic/ripple_effect.py
typedhtml/ionic/textarea.py
typedhtml/py.typed
typedhtml/svg.py
typedhtml/tags.py
typedhtml/ui5/__init__.py
typedhtml/ui5/avatar.py
typedhtml/ui5/badge.py
typedhtml/ui5/bar.py
typedhtml/ui5/barcode_scanner_dialog.py
typedhtml/ui5/base.py
typedhtml/ui5/breadcrumbs.py
typedhtml/ui5/busy_indicator.py
typedhtml/ui5/button.py
typedhtml/ui5/calendar.py
typedhtml/ui5/card.py
typedhtml/ui5/carousel.py
typedhtml/ui5/checkbox.py
typedhtml/ui5/color_palette.py
typedhtml/ui5/color_picker.py
typedhtml/ui5/combobox.py
typedhtml/ui5/datepicker.py
typedhtml/ui5/daterange_picker.py
typedhtml/ui5/datetime_picker.py
typedhtml/ui5/dialog.py
typedhtml/ui5/dynamic_side_content.py
typedhtml/ui5/file_uploader.py
typedhtml/ui5/flexible_column_layout.py
typedhtml/ui5/icon.py
typedhtml/ui5/illustrated_message.py
typedhtml/ui5/input.py
typedhtml/ui5/label.py
typedhtml/ui5/link.py
typedhtml/ui5/list.py
typedhtml/ui5/media_gallery.py
typedhtml/ui5/menu.py
typedhtml/ui5/message_strip.py
typedhtml/ui5/multi_combobox.py
typedhtml/ui5/multi_input.py
typedhtml/ui5/notification_list_group.py
typedhtml/ui5/notification_list_item.py
typedhtml-0.2.22.dist-info/METADATA
typedhtml-0.2.22.dist-info/WHEEL
typedhtml-0.2.22.dist-info/RECORD
